<?xml version="1.0" encoding="utf-8"?>
<clothingItem>
	<m_MaleModel>media\models_X\Skinned\BackPacks\SheetSlingBag_RHand.x</m_MaleModel>
	<m_FemaleModel>media\models_X\Skinned\BackPacks\SheetSlingBag_RHand.x</m_FemaleModel>
	<m_GUID>48efff6c-7921-4cc1-b3f6-a8bc88df2fda</m_GUID>
	<m_Static>false</m_Static>
	<m_AllowRandomHue>false</m_AllowRandomHue>
	<m_AllowRandomTint>false</m_AllowRandomTint>
	<m_AttachBone></m_AttachBone>
	<textureChoices>clothes\bag\sheetslingbag</textureChoices>
</clothingItem>