<?xml version="1.0" encoding="utf-8"?>
<clothingItem>
	<m_MaleModel>media\models_X\Skinned\BackPacks\TakeoutBox_Classic_RHand.X</m_MaleModel>
	<m_FemaleModel>media\models_X\Skinned\BackPacks\TakeoutBox_Classic_RHand.X</m_FemaleModel>
	<m_GUID>acb80366-9fbd-41f9-896a-c0fb29c34f1a</m_GUID>
	<m_Static>false</m_Static>
	<m_AllowRandomHue>false</m_AllowRandomHue>
	<m_AllowRandomTint>false</m_AllowRandomTint>
	<m_AttachBone></m_AttachBone>
	<textureChoices>worlditems\TakeoutBox_Classic</textureChoices>
</clothingItem>